IOperator/AngularMomentumOperators.py
IOperator/__init__.py
ioperator-0.1.0.dist-info/METADATA
ioperator-0.1.0.dist-info/WHEEL
ioperator-0.1.0.dist-info/top_level.txt
ioperator-0.1.0.dist-info/RECORD
