Metadata-Version: 2.4
Name: IOperator
Version: 0.1.0
Summary: Spin Dyamics library
Author: Quentin Stern
Dynamic: author
Dynamic: summary
